sqsfn/__init__.py
sqsfn/sqsutils.py
bayis_sqs_callback-0.0.4.dist-info/LICENSE.md
bayis_sqs_callback-0.0.4.dist-info/METADATA
bayis_sqs_callback-0.0.4.dist-info/WHEEL
bayis_sqs_callback-0.0.4.dist-info/top_level.txt
bayis_sqs_callback-0.0.4.dist-info/RECORD
