Metadata-Version: 2.1
Name: bayis-sqs-callback
Version: 0.0.4
Summary: AWS SQS item processing callback
Home-page: https://github.com/bayinfosys/sqsfn
Author: ed
Author-email: ed@bayis.co.uk
Classifier: Programming Language :: Python :: 3
Classifier: Operating System :: OS Independent
Requires-Python: >=3.7
License-File: LICENSE.md
Requires-Dist: boto3
Provides-Extra: tests
Requires-Dist: hypothesis ; extra == 'tests'
Requires-Dist: mock ; extra == 'tests'
Requires-Dist: moto ; extra == 'tests'
Requires-Dist: pytest ; extra == 'tests'
